databasez/__init__.py
databasez/interfaces.py
databasez/py.typed
databasez/sqlalchemy.py
databasez/testclient.py
databasez/types.py
databasez/utils.py
databasez/core/__init__.py
databasez/core/asgi.py
databasez/core/connection.py
databasez/core/database.py
databasez/core/databaseurl.py
databasez/core/transaction.py
databasez/dialects/dbapi2.py
databasez/dialects/jdbc.py
databasez/overwrites/dbapi2.py
databasez/overwrites/jdbc.py
databasez/overwrites/mssql.py
databasez/overwrites/mysql.py
databasez/overwrites/postgres.py
databasez/overwrites/postgresql.py
databasez/overwrites/sqlite.py
databasez-0.11.3.dist-info/METADATA
databasez-0.11.3.dist-info/WHEEL
databasez-0.11.3.dist-info/licenses/LICENSE
databasez-0.11.3.dist-info/RECORD
