Metadata-Version: 2.4
Name: databasez
Version: 0.11.3
Summary: Async database support for Python.
Project-URL: Homepage, https://github.com/dymmond/databasez
Project-URL: Documentation, https://databasez.tarsild/
Project-URL: Changelog, https://databasez.dymmond.com/release-notes/
Project-URL: Funding, https://github.com/sponsors/tarsil
Project-URL: Source, https://github.com/dymmond/databasez
Author-email: Tiago Silva <tiago.arasilva@gmail.com>
License-File: LICENSE
Keywords: asyncio,esmerald,jdbc,mysql,postgres,saffier,sqlalchemy,sqlite
Classifier: Development Status :: 5 - Production/Stable
Classifier: Environment :: Web Environment
Classifier: Framework :: AnyIO
Classifier: Framework :: AsyncIO
Classifier: Intended Audience :: Developers
Classifier: Intended Audience :: Information Technology
Classifier: Intended Audience :: System Administrators
Classifier: License :: OSI Approved :: BSD License
Classifier: Operating System :: OS Independent
Classifier: Programming Language :: Python
Classifier: Programming Language :: Python :: 3
Classifier: Programming Language :: Python :: 3 :: Only
Classifier: Programming Language :: Python :: 3.9
Classifier: Programming Language :: Python :: 3.10
Classifier: Programming Language :: Python :: 3.11
Classifier: Programming Language :: Python :: 3.12
Classifier: Programming Language :: Python :: 3.13
Classifier: Topic :: Internet
Classifier: Topic :: Software Development
Classifier: Topic :: Software Development :: Libraries
Classifier: Topic :: Software Development :: Libraries :: Application Frameworks
Classifier: Topic :: Software Development :: Libraries :: Python Modules
Classifier: Typing :: Typed
Requires-Python: >=3.9
Requires-Dist: orjson
Requires-Dist: sqlalchemy[asyncio]<2.1,>=2.0.25
Provides-Extra: aiomysql
Requires-Dist: aiomysql; extra == 'aiomysql'
Provides-Extra: aioodbc
Requires-Dist: aioodbc; extra == 'aioodbc'
Provides-Extra: aiosqlite
Requires-Dist: aiosqlite; extra == 'aiosqlite'
Provides-Extra: all
Requires-Dist: aiomysql; extra == 'all'
Requires-Dist: aioodbc; extra == 'all'
Requires-Dist: aiosqlite; extra == 'all'
Requires-Dist: asyncmy; extra == 'all'
Requires-Dist: asyncpg; extra == 'all'
Requires-Dist: jpype1; extra == 'all'
Provides-Extra: asyncpg
Requires-Dist: asyncpg; extra == 'asyncpg'
Provides-Extra: jdbc
Requires-Dist: jpype1; extra == 'jdbc'
Provides-Extra: mysql
Requires-Dist: asyncmy; extra == 'mysql'
Provides-Extra: odbc
Requires-Dist: aioodbc; extra == 'odbc'
Provides-Extra: postgresql
Requires-Dist: asyncpg; extra == 'postgresql'
Provides-Extra: sqlite
Requires-Dist: aiosqlite; extra == 'sqlite'
Provides-Extra: testing
